CHANGES.txt
README.md
README.txt
setup.py
tomcom/__init__.py
tomcom.plone.ptregistry.egg-info/PKG-INFO
tomcom.plone.ptregistry.egg-info/SOURCES.txt
tomcom.plone.ptregistry.egg-info/dependency_links.txt
tomcom.plone.ptregistry.egg-info/entry_points.txt
tomcom.plone.ptregistry.egg-info/namespace_packages.txt
tomcom.plone.ptregistry.egg-info/not-zip-safe
tomcom.plone.ptregistry.egg-info/requires.txt
tomcom.plone.ptregistry.egg-info/top_level.txt
tomcom/plone/__init__.py
tomcom/plone/ptregistry/__init__.py
tomcom/plone/ptregistry/configure.zcml
tomcom/plone/ptregistry/meta.py
tomcom/plone/ptregistry/meta.zcml